{
  "entities": {
    "stations": {
      "1": {
        "x": 5901.202243435863,
        "y": 2579.150855767895,
        "capacity": 2
      },
      "2": {
        "x": 11176.438059665546,
        "y": 5931.579948387285,
        "capacity": 2
      },
      "3": {
        "x": 469.2699061289841,
        "y": 1304.6222255659752,
        "capacity": 2
      },
      "4": {
        "x": 16168.916785774054,
        "y": 3484.841920486239,
        "capacity": 2
      },
      "5": {
        "x": 2936.3637531868767,
        "y": 7951.50967128139,
        "capacity": 2
      }
    },
    "drones": {
      "1": {
        "home": 3
      },
      "2": {
        "home": 3
      },
      "3": {
        "home": 3
      },
      "4": {
        "home": 1
      },
      "5": {
        "home": 5
      }
    },
    "deliveries": {
      "1": {
        "src": 3,
        "dst": 4,
        "weight": 1.0119075514208307
      },
      "2": {
        "src": 2,
        "dst": 5,
        "weight": 0.9471757751702903
      },
      "3": {
        "src": 1,
        "dst": 3,
        "weight": 0.014422668648813364
      }
    }
  }
}